<?xml version="1.0" encoding="UTF-8"?>
<con:restMockAction name="/v2/pet" method="POST" resourcePath="/v2/pet" id="d4517904-1566-4acc-98df-a571277ea349" xmlns:con="http://eviware.com/soapui/config">
  <con:settings>
    <con:setting id="d4517904-1566-4acc-98df-a571277ea349fileName">%2Fv2%2Fpet</con:setting>
  </con:settings>
  <con:dispatchStyle>SEQUENCE</con:dispatchStyle>
  <con:dispatchConfig/>
  <con:dispatchXPath/>
  <con:routeScript/>
  <con:response name="Response 1" id="b289dd79-e1a5-4199-b55b-976f2cd05992" httpResponseStatus="405" mediaType="application/xml" dataSource="">
    <con:settings/>
    <con:responseContent/>
  </con:response>
  <con:response name="Response 2" id="674cc194-401e-4d43-9e10-0c0af6e69d44" httpResponseStatus="405" mediaType="application/json" dataSource="">
    <con:settings/>
    <con:responseContent/>
  </con:response>
</con:restMockAction>
