<?xml version="1.0" encoding="UTF-8"?>
<con:restMockAction name="/v2/pet" method="PUT" resourcePath="/v2/pet" id="6d36554c-15a6-491a-91b0-2ff9ed6d9157" xmlns:con="http://eviware.com/soapui/config">
  <con:settings>
    <con:setting id="6d36554c-15a6-491a-91b0-2ff9ed6d9157fileName">%2Fv2%2Fpet1</con:setting>
  </con:settings>
  <con:dispatchStyle>SEQUENCE</con:dispatchStyle>
  <con:dispatchConfig/>
  <con:dispatchXPath/>
  <con:routeScript/>
  <con:response name="Response 1" id="392fcd1e-58b6-4669-82d9-5c963b08b43a" httpResponseStatus="400" mediaType="application/xml" dataSource="">
    <con:settings/>
    <con:responseContent/>
  </con:response>
  <con:response name="Response 2" id="796b57f7-87c4-4915-8de4-d5f31bf8c7e9" httpResponseStatus="400" mediaType="application/json" dataSource="">
    <con:settings/>
    <con:responseContent/>
  </con:response>
  <con:response name="Response 3" id="ab5ded0b-45f9-4f66-ad83-9029cd9d2628" httpResponseStatus="404" mediaType="application/xml" dataSource="">
    <con:settings/>
    <con:responseContent/>
  </con:response>
  <con:response name="Response 4" id="0882462c-c6c7-4527-b591-11786515ba20" httpResponseStatus="404" mediaType="application/json" dataSource="">
    <con:settings/>
    <con:responseContent/>
  </con:response>
  <con:response name="Response 5" id="46870b24-2621-4649-8d7f-e70548dfbdd0" httpResponseStatus="405" mediaType="application/xml" dataSource="">
    <con:settings/>
    <con:responseContent/>
  </con:response>
  <con:response name="Response 6" id="3813e3d2-470b-47c1-9446-5107f6651d59" httpResponseStatus="405" mediaType="application/json" dataSource="">
    <con:settings/>
    <con:responseContent/>
  </con:response>
</con:restMockAction>
